cdx_tf/__init__.py
cdx_tf/clip.py
cdx_tf/gym.py
cdx_tf/layers.py
cdx_tf/models.py
cdx_tf/monetary_utility.py
cdx_tf/optimizer.py
cdx_tf/util.py
cdx_tf-0.1.4.dist-info/LICENSE
cdx_tf-0.1.4.dist-info/METADATA
cdx_tf-0.1.4.dist-info/WHEEL
cdx_tf-0.1.4.dist-info/top_level.txt
cdx_tf-0.1.4.dist-info/RECORD
