Metadata-Version: 2.1
Name: cdx-tf
Version: 0.1.4
Summary: Basic Python tools
Home-page: https://github.com/hansbuehler/cdx_tf
Author: Hans Buehler
Author-email: github@buehler.london
Classifier: Programming Language :: Python :: 3
Classifier: License :: OSI Approved :: MIT License
Classifier: Operating System :: OS Independent
Requires-Python: >=3.7
License-File: LICENSE
Requires-Dist: numpy (>=1.23)
Requires-Dist: pandas (>=1.5)
Requires-Dist: scipy (>=1.10)
Requires-Dist: matplotlib (>=3.7)
Requires-Dist: sortedcontainers (>=2.4)
Requires-Dist: tensorflow (>=2.10)
Requires-Dist: psutil
Requires-Dist: cdxbasics (>=0.2.40)
